{
  "source_id": "src-mcconaughey-greenlights-2020",
  "source_type": "book",
  "speaker": "Matthew McConaughey",
  "show_or_platform": "Greenlights",
  "episode_or_content_title": "Greenlights",
  "episode_or_content_date": "2020-10-20",
  "source_url": "https://www.penguinrandomhouse.com/books/635407/greenlights-by-matthew-mcconaughey/",
  "video_provider": "none",
  "video_id": "",
  "video_url": "",
  "embed_url": "",
  "official_channel": "Crown / Penguin Random House",
  "official_channel_url": "https://www.penguinrandomhouse.com/books/635407/greenlights-by-matthew-mcconaughey/",
  "transcript_url": "",
  "transcript_available": false,
  "transcript_source": "book text (not ingested verbatim)",
  "transcript_verified": false,
  "timestamp_verified": false,
  "media_available": true,
  "media_verification_status": "not_applicable",
  "source_confidence": "high",
  "source_score": null,
  "verification_notes": "Created 2026-05 when sio-mcconaughey-go-to-zero-2020 was re-sourced here from a misattributed Tim Ferriss episode. The $14.5M rom-com refusal (~2010) and the 'if I couldn't do what I wanted...' stance are documented in McConaughey's memoir Greenlights (Crown/PRH, ISBN 9780593139158, Oct 2020) and widely reported (Penguin Random House book page, IndieWire, ScreenRant, etc.). Official publisher URL verified via web search (2026-05). Text-only source — no embeddable video. SIO excerpt is a faithful paraphrase pending a brief verbatim quote + page citation before approval.",
  "rights_or_usage_notes": "Published book. Brief documented quotes for attribution; link to the official publisher page. Do not reproduce extended passages.",
  "sios": ["sio-mcconaughey-go-to-zero-2020"]
}
