{
  "source_id": "src-robertgreene-uncertainty-2024",
  "source_type": "solo educational",
  "speaker": "Robert Greene",
  "show_or_platform": "Robert Greene Official",
  "episode_or_content_title": "Robert Greene: The Dance with Uncertainty",
  "episode_or_content_date": "2024-03-25",
  "source_url": "https://www.youtube.com/watch?v=ocVczQeUDvY",
  "video_provider": "youtube",
  "video_id": "ocVczQeUDvY",
  "video_url": "https://www.youtube.com/watch?v=ocVczQeUDvY",
  "embed_url": "https://www.youtube-nocookie.com/embed/ocVczQeUDvY?start=149&end=190",
  "official_channel": "Robert Greene Official",
  "official_channel_url": "https://www.youtube.com/@RobertGreeneOfficial",
  "channel_id": "UC-qsP49Ai2GymJgyKX38l1w",
  "transcript_url": "",
  "transcript_available": true,
  "transcript_verified": true,
  "timestamp_verified": true,
  "media_available": true,
  "media_verification_status": "verified",
  "source_confidence": "high",
  "verification_notes": "Verified 2026-06-04: speaker's own official channel (Robert Greene Official, channel_id UC-qsP49Ai2GymJgyKX38l1w). Excerpt confirmed verbatim in English auto-captions at 2:29–3:10 (yt-dlp; ASR misspells surname 'Green' — corrected, no wording changed). Embed via youtube-nocookie.",
  "rights_or_usage_notes": "Speaker's own official channel. Brief verbatim quote for attribution; embed/link only.",
  "sios": [
    "sio-greene-good-uncertainty-2024"
  ]
}
