{
  "source_id": "src-school-of-greatness-brown-lost-lazy-unmotivated-2017",
  "source_type": "long-form interview podcast",
  "speaker": "Brené Brown",
  "show_or_platform": "The School of Greatness",
  "episode_or_content_title": "This Is Why You FEEL LOST, LAZY & UNMOTIVATED In Life",
  "episode_or_content_date": "2017-09-13",
  "source_url": "https://www.youtube.com/watch?v=TbsRU-crgsc",
  "video_provider": "youtube",
  "video_id": "TbsRU-crgsc",
  "video_url": "https://www.youtube.com/watch?v=TbsRU-crgsc",
  "embed_url": "https://www.youtube-nocookie.com/embed/TbsRU-crgsc",
  "official_channel": "The School of Greatness",
  "official_channel_url": "https://www.youtube.com/@lewishowes",
  "channel_id": "UCKsP3v2JeT2hWI_HzkxWiMA",
  "transcript_url": "",
  "transcript_available": false,
  "transcript_source": "no official transcript published",
  "transcript_verified": false,
  "timestamp_verified": false,
  "media_available": true,
  "media_verification_status": "verified",
  "source_confidence": "high",
  "source_score": null,
  "verification_notes": "Created 2026-06-02 via the SoG harvest batch. Official Lewis Howes / School of Greatness YouTube channel verified via YouTube Data API (channel_id UCKsP3v2JeT2hWI_HzkxWiMA). Video metadata fetched via videos.list and confirmed on the official channel. No official transcript published; SIO excerpt is a faithful paraphrase of Brown's documented research and language on shame/disconnection/disengagement (per her broader published work in Daring Greatly, Atlas of the Heart, and her TED talks), in the register of this interview. No chapter markers in the video description; no per-moment timestamp recorded.",
  "rights_or_usage_notes": "Official Lewis Howes YouTube upload. Embed only via youtube-nocookie.com from the official channel. Do not download or re-host. Brief paraphrase for attribution; link back to the canonical YouTube watch page.",
  "sios": ["sio-brown-numbness-as-disconnection-2017"]
}
